caldav2ics.py
caldav2ics-0.1.1.dist-info/licenses/LICENSE
caldav2ics-0.1.1.dist-info/METADATA
caldav2ics-0.1.1.dist-info/WHEEL
caldav2ics-0.1.1.dist-info/entry_points.txt
caldav2ics-0.1.1.dist-info/top_level.txt
caldav2ics-0.1.1.dist-info/RECORD
