Metadata-Version: 2.4
Name: caldav2ics
Version: 0.1.1
Summary: Cache CalDAV calendars in static .ICS files.
Author-email: Tim Hörmann <pypi@audivir.de>
License-Expression: MIT
Project-URL: Homepage, https://github.com/audivir/caldav2ics
Project-URL: Repository, https://github.com/audivir/caldav2ics
Classifier: Programming Language :: Python :: 3
Requires-Python: >=3.9
License-File: LICENSE
Requires-Dist: caldav
Requires-Dist: doctyper
Requires-Dist: icalendar
Requires-Dist: msgspec[toml]
Requires-Dist: typing-extensions
Provides-Extra: dev
Requires-Dist: ruff; extra == "dev"
Requires-Dist: mypy; extra == "dev"
Requires-Dist: pytest; extra == "dev"
Requires-Dist: coverage[toml]; extra == "dev"
Requires-Dist: vulture; extra == "dev"
Dynamic: license-file
